api/__init__.py
api/api_keys.py
api/config.py
api/jwt_utils.py
api/models.py
api/cli/__init__.py
api/cli/__main__.py
api/cli/apikey.py
api/cli/app.py
api/cli/db.py
api/cli/env.py
api/cli/folder.py
api/cli/output.py
api/cli/server.py
api/cli/verbose.py
api/cli/wf/__init__.py
api/cli/wf/add.py
api/cli/wf/common.py
api/cli/wf/delete.py
api/cli/wf/link.py
api/cli/wf/list_cmd.py
api/cli/wf/pull.py
api/cli/wf/push.py
api/cli/wf/search.py
api/cli/wf/stats.py
api/db/__init__.py
api/db/apikeys.py
api/db/backup.py
api/db/base.py
api/db/core.py
api/db/folders.py
api/db/schema.py
api/db/servers.py
api/transports/__init__.py
api/transports/base.py
api/transports/sftp.py
api/workflow/__init__.py
api/workflow/crud.py
api/workflow/folder_path.py
api/workflow/folder_sync.py
api/workflow/http_client.py
api/workflow/main.py
api/workflow/n8n_api.py
api/workflow/n8n_internal_api.py
api/workflow/server_resolver.py
api/workflow/ssl_utils.py
api/workflow/types.py
n8n_deploy-0.9.1.dist-info/licenses/LICENSE
n8n_deploy-0.9.1.dist-info/METADATA
n8n_deploy-0.9.1.dist-info/WHEEL
n8n_deploy-0.9.1.dist-info/entry_points.txt
n8n_deploy-0.9.1.dist-info/top_level.txt
n8n_deploy-0.9.1.dist-info/RECORD
