Metadata-Version: 2.4
Name: n8n-deploy
Version: 0.9.1
Summary: n8n-deploy - a simple N8N Workflow Manager with SQLite metadata store
Author-email: Lehcode <53556648+lehcode@users.noreply.github.com>
Maintainer-email: Lehcode <53556648+lehcode@users.noreply.github.com>
License: MIT
Project-URL: Homepage, https://github.com/lehcode/n8n-deploy
Project-URL: Documentation, https://lehcode.github.io/n8n-deploy
Project-URL: Repository, https://github.com/lehcode/n8n-deploy.git
Project-URL: Bug Tracker, https://github.com/lehcode/n8n-deploy/issues
Project-URL: Changelog, https://github.com/lehcode/n8n-deploy/releases
Keywords: n8n,wf,automation,cli,sqlite,deployment
Classifier: Development Status :: 4 - Beta
Classifier: Intended Audience :: Developers
Classifier: Intended Audience :: System Administrators
Classifier: Operating System :: OS Independent
Classifier: Programming Language :: Python :: 3
Classifier: Programming Language :: Python :: 3.8
Classifier: Programming Language :: Python :: 3.9
Classifier: Programming Language :: Python :: 3.10
Classifier: Programming Language :: Python :: 3.11
Classifier: Programming Language :: Python :: 3.12
Classifier: Topic :: Software Development :: Libraries :: Python Modules
Classifier: Topic :: System :: Systems Administration
Classifier: Topic :: Database
Classifier: Topic :: Internet :: WWW/HTTP :: Dynamic Content
Classifier: Environment :: Console
Classifier: Natural Language :: English
Requires-Python: >=3.8
License-File: LICENSE
Requires-Dist: click>=8.0.0
Requires-Dist: requests>=2.28.0
Requires-Dist: pydantic>=2.0.0
Requires-Dist: rich>=13.0.0
Requires-Dist: python-dateutil>=2.8.0
Requires-Dist: tabulate>=0.9.0
Requires-Dist: colorama>=0.4.0
Requires-Dist: gitpython>=3.1.0
Requires-Dist: paramiko>=3.0.0
Provides-Extra: dev
Requires-Dist: pytest>=7.0.0; extra == "dev"
Requires-Dist: black>=22.0.0; extra == "dev"
Requires-Dist: flake8>=4.0.0; extra == "dev"
Requires-Dist: mypy>=1.0.0; extra == "dev"
Requires-Dist: pre-commit>=2.20.0; extra == "dev"
Requires-Dist: types-requests>=2.31.0; extra == "dev"
Requires-Dist: types-click>=7.1.8; extra == "dev"
Requires-Dist: python-dotenv>=1.0.0; extra == "dev"
Requires-Dist: radon>=6.0.0; extra == "dev"
Requires-Dist: vulture>=2.10; extra == "dev"
Requires-Dist: rope>=1.12.0; extra == "dev"
Requires-Dist: types-paramiko>=3.0.0; extra == "dev"
Requires-Dist: types-assertpy>=1.1.0; extra == "dev"
Provides-Extra: test
Requires-Dist: pytest>=7.0.0; extra == "test"
Requires-Dist: pytest-cov>=4.0.0; extra == "test"
Requires-Dist: pytest-mock>=3.10.0; extra == "test"
Requires-Dist: pytest-order>=1.0.0; extra == "test"
Requires-Dist: pytest-testmon>=2.1.0; extra == "test"
Requires-Dist: assertpy>=1.1; extra == "test"
Requires-Dist: hypothesis>=6.0.0; extra == "test"
Dynamic: license-file
